stellar_webscrape/__init__.py
stellar_webscrape/config.py
stellar_webscrape/scraper.py
stellar_webscrape/utils.py
tests/__init__.py
tests/test_scraper.py
stellar_webscrape-0.1.0.dist-info/LICENSE
stellar_webscrape-0.1.0.dist-info/METADATA
stellar_webscrape-0.1.0.dist-info/WHEEL
stellar_webscrape-0.1.0.dist-info/top_level.txt
stellar_webscrape-0.1.0.dist-info/RECORD
