Metadata-Version: 2.1
Name: stellar_webscrape
Version: 0.1.0
Summary: A Python package for web scraping.
Home-page: https://github.com/nikithakrishnan/stellar-webscrape
Author: Nikitha Krishnan
Author-email: Nikitha Krishnan <nikithakrishnan123@gmail.com>
Classifier: Programming Language :: Python :: 3
Classifier: License :: OSI Approved :: MIT License
Requires-Python: >=3.6
License-File: LICENSE
